pymcbdsc/__init__.py
pymcbdsc/__main__.py
pymcbdsc/constants.py
pymcbdsc/docker.py
pymcbdsc/downloader.py
pymcbdsc/exceptions.py
pymcbdsc/utils.py
pymcbdsc-0.3.1.data/data/share/mcbdsc/docker/Dockerfile
pymcbdsc-0.3.1.data/data/share/mcbdsc/docker/entrypoint.sh
pymcbdsc-0.3.1.data/data/share/mcbdsc/docker/env_files/example.env
tests/__init__.py
tests/pymcbdsc/__init__.py
tests/pymcbdsc/test_docker.py
tests/pymcbdsc/test_downloader.py
tests/pymcbdsc/test_utils.py
pymcbdsc-0.3.1.dist-info/LICENSE
pymcbdsc-0.3.1.dist-info/METADATA
pymcbdsc-0.3.1.dist-info/WHEEL
pymcbdsc-0.3.1.dist-info/entry_points.txt
pymcbdsc-0.3.1.dist-info/top_level.txt
pymcbdsc-0.3.1.dist-info/RECORD
